follower.cp311-win_amd64.pyd
pyfollower/Simulator.py
pyfollower/__init__.py
pyfollower-0.1.4.dist-info/METADATA
pyfollower-0.1.4.dist-info/WHEEL
pyfollower-0.1.4.dist-info/top_level.txt
pyfollower-0.1.4.dist-info/RECORD
