Metadata-Version: 2.1
Name: pyfollower
Version: 0.1.4
Summary: Follower Crowd Simulation
Author-email: Rabbytr <dejavu.rabbyt@gmail.com>
License: Apache License 2.0
Keywords: Crowd,Simulation
Classifier: Programming Language :: Python :: 3
Classifier: Programming Language :: Python :: 3.7
Classifier: Programming Language :: Python :: 3.8
Classifier: Programming Language :: Python :: 3.9
Classifier: Programming Language :: Python :: 3.10
Classifier: Programming Language :: Python :: 3.11
Classifier: License :: OSI Approved :: Apache Software License
Classifier: Operating System :: OS Independent
Requires-Python: >=3.7
Requires-Dist: setuptools >=42.0
Requires-Dist: wheel
